examples/type_validation_example.py
hibber_url_analyzer-1.0.0.dist-info/licenses/LICENSE
migrations/20250805_183000_initialize_url_schema.py
plugins/examples/markdown_report_generator.py
plugins/examples/social_media_classifier.py
scripts/analyze_complexity.py
scripts/build_dist.py
scripts/check_dependencies.py
scripts/check_features.py
scripts/check_license_headers.py
scripts/install.py
scripts/profile_memory_usage.py
scripts/run_mutation_tests.py
scripts/setup_precommit.py
scripts/test_documentation.py
scripts/track_technical_debt.py
scripts/update_dependencies.py
tests/__init__.py
tests/example_fixture_usage.py
tests/fixtures.py
tests/integration/test_end_to_end.py
tests/integration/test_integration.py
tests/integration/test_integration_suite.py
tests/performance/test_memory_profiler.py
tests/performance/test_performance_benchmarks.py
tests/performance/test_performance_integration.py
tests/performance/test_performance_monitoring.py
tests/performance/test_profiling.py
tests/security/test_penetration.py
tests/security/test_security.py
tests/security/test_security_regression.py
tests/unit/analysis/test_advanced_analytics.py
tests/unit/analysis/test_relationship_mapping.py
tests/unit/api/test_api.py
tests/unit/automation/test_automation.py
tests/unit/collaboration/test_collaboration.py
tests/unit/core/test_url_analyzer.py
tests/unit/data/test_export_features.py
tests/unit/infrastructure/test_migration.py
tests/unit/plugins/test_plugin_architecture.py
tests/unit/reporting/test_report_builders.py
tests/unit/reporting/test_report_generation.py
tests/unit/reporting/test_templates.py
tests/unit/reporting/test_visualization.py
tests/unit/utils/test_babel_error.py
tests/unit/utils/test_concurrent_operations.py
tests/unit/utils/test_enhanced_cache.py
tests/unit/utils/test_enhanced_parallel.py
tests/unit/utils/test_logging.py
tests/unit/utils/test_logging_simple.py
tests/unit/validation/test_property_based.py
tests/unit/validation/test_validation.py
url_analyzer/__init__.py
url_analyzer/__main__.py
hibber_url_analyzer-1.0.0.dist-info/METADATA
hibber_url_analyzer-1.0.0.dist-info/WHEEL
hibber_url_analyzer-1.0.0.dist-info/entry_points.txt
hibber_url_analyzer-1.0.0.dist-info/top_level.txt
hibber_url_analyzer-1.0.0.dist-info/RECORD
