Metadata-Version: 2.4
Name: hibber-url-analyzer
Version: 1.0.0
Summary: A tool for analyzing, categorizing, and reporting on URLs from browsing history or other sources
Home-page: https://github.com/url-analyzer/url-analyzer
Author: URL Analyzer Team
Author-email: URL Analyzer Team <contact@url-analyzer.dev>
Maintainer-email: URL Analyzer Team <contact@url-analyzer.dev>
License: MIT
Project-URL: Homepage, https://github.com/Hibber/url-analyzer
Project-URL: Bug Tracker, https://github.com/Hibber/url-analyzer/issues
Project-URL: Documentation, https://github.com/Hibber/url-analyzer/blob/main/docs
Project-URL: Source Code, https://github.com/Hibber/url-analyzer
Project-URL: Repository, https://github.com/Hibber/url-analyzer.git
Keywords: url,analysis,web,browsing,history,categorization,reporting
Classifier: Development Status :: 4 - Beta
Classifier: Intended Audience :: End Users/Desktop
Classifier: Intended Audience :: Information Technology
Classifier: License :: OSI Approved :: MIT License
Classifier: Programming Language :: Python :: 3
Classifier: Programming Language :: Python :: 3.8
Classifier: Programming Language :: Python :: 3.9
Classifier: Programming Language :: Python :: 3.10
Classifier: Programming Language :: Python :: 3.11
Classifier: Programming Language :: Python :: 3.12
Classifier: Topic :: Internet :: WWW/HTTP
Classifier: Topic :: Scientific/Engineering :: Information Analysis
Classifier: Topic :: Utilities
Requires-Python: >=3.8
License-File: LICENSE
Requires-Dist: pandas>=1.3.0
Requires-Dist: numpy>=1.20.0
Requires-Dist: jinja2>=3.1.6
Requires-Dist: flask>=2.3.0
Requires-Dist: flask-wtf>=1.2.0
Requires-Dist: flask-babel>=3.1.0
Requires-Dist: werkzeug>=2.3.0
Requires-Dist: email-validator>=2.0.0
Requires-Dist: itsdangerous>=2.1.0
Requires-Dist: networkx>=2.6.0
Provides-Extra: url-fetching
Requires-Dist: requests>=2.32.4; extra == "url-fetching"
Provides-Extra: html-parsing
Requires-Dist: beautifulsoup4>=4.9.0; extra == "html-parsing"
Requires-Dist: lxml>=4.6.0; extra == "html-parsing"
Provides-Extra: domain-extraction
Requires-Dist: tldextract>=3.1.0; extra == "domain-extraction"
Provides-Extra: visualization
Requires-Dist: plotly>=5.3.0; extra == "visualization"
Provides-Extra: geolocation
Requires-Dist: geoip2>=4.6.0; extra == "geolocation"
Requires-Dist: pycountry>=22.3.5; extra == "geolocation"
Provides-Extra: pdf-export
Requires-Dist: weasyprint>=57.1; extra == "pdf-export"
Provides-Extra: progress
Requires-Dist: tqdm>=4.60.0; extra == "progress"
Provides-Extra: excel
Requires-Dist: openpyxl>=3.0.0; extra == "excel"
Provides-Extra: terminal-ui
Requires-Dist: rich>=13.3.0; extra == "terminal-ui"
Requires-Dist: prompt_toolkit>=3.0.30; extra == "terminal-ui"
Provides-Extra: system
Requires-Dist: psutil>=5.9.0; extra == "system"
Provides-Extra: ml-analysis
Requires-Dist: scipy>=1.8.0; extra == "ml-analysis"
Requires-Dist: scikit-learn>=1.0.0; extra == "ml-analysis"
Requires-Dist: nltk>=3.7.0; extra == "ml-analysis"
Provides-Extra: dev
Requires-Dist: pytest>=7.3.1; extra == "dev"
Requires-Dist: pytest-cov>=4.1.0; extra == "dev"
Requires-Dist: hypothesis>=6.82.0; extra == "dev"
Requires-Dist: mutmut>=2.4.0; extra == "dev"
Requires-Dist: mypy>=1.0.0; extra == "dev"
Requires-Dist: black>=23.0.0; extra == "dev"
Requires-Dist: isort>=5.0.0; extra == "dev"
Requires-Dist: flake8>=6.0.0; extra == "dev"
Requires-Dist: radon>=6.0.0; extra == "dev"
Requires-Dist: pylint>=2.17.0; extra == "dev"
Requires-Dist: bandit>=1.7.5; extra == "dev"
Requires-Dist: safety>=2.3.5; extra == "dev"
Provides-Extra: all
Requires-Dist: requests>=2.32.4; extra == "all"
Requires-Dist: beautifulsoup4>=4.9.0; extra == "all"
Requires-Dist: lxml>=4.6.0; extra == "all"
Requires-Dist: tldextract>=3.1.0; extra == "all"
Requires-Dist: plotly>=5.3.0; extra == "all"
Requires-Dist: geoip2>=4.6.0; extra == "all"
Requires-Dist: pycountry>=22.3.5; extra == "all"
Requires-Dist: weasyprint>=57.1; extra == "all"
Requires-Dist: tqdm>=4.60.0; extra == "all"
Requires-Dist: openpyxl>=3.0.0; extra == "all"
Requires-Dist: rich>=13.3.0; extra == "all"
Requires-Dist: prompt_toolkit>=3.0.30; extra == "all"
Requires-Dist: psutil>=5.9.0; extra == "all"
Requires-Dist: scipy>=1.8.0; extra == "all"
Requires-Dist: scikit-learn>=1.0.0; extra == "all"
Requires-Dist: nltk>=3.7.0; extra == "all"
Dynamic: author
Dynamic: home-page
Dynamic: license-file
Dynamic: requires-python
